cinemaot/__init__.py
cinemaot/benchmark.py
cinemaot/cinemaot.py
cinemaot/sinkhorn_knopp.py
cinemaot/utils.py
cinemaot-0.0.5.dist-info/LICENSE
cinemaot-0.0.5.dist-info/METADATA
cinemaot-0.0.5.dist-info/WHEEL
cinemaot-0.0.5.dist-info/top_level.txt
cinemaot-0.0.5.dist-info/RECORD
