Metadata-Version: 2.1
Name: cinemaot
Version: 0.0.5
Summary: Causal INdependent Effect Module Attribution + Optimal Transport
Home-page: https://github.com/vandijklab/CINEMA-OT
Author: Mingze Dong
Author-email: mingze.dong@yale.edu
License: UNKNOWN
Project-URL: Bug Tracker, https://github.com/vandijklab/CINEMA-OT/issues
Platform: UNKNOWN
Classifier: Programming Language :: Python :: 3
Classifier: Development Status :: 2 - Pre-Alpha
Classifier: Operating System :: OS Independent
Requires-Python: >=3.7
License-File: LICENSE
Requires-Dist: numpy
Requires-Dist: pandas
Requires-Dist: scanpy
Requires-Dist: scikit-learn
Requires-Dist: scipy
Requires-Dist: statsmodels
Requires-Dist: anndata
